sal/__init__.py
sal/id/__init__.py
sal/id/indonesia_ner.py
salang-0.0.2.dist-info/LICENSE
salang-0.0.2.dist-info/METADATA
salang-0.0.2.dist-info/WHEEL
salang-0.0.2.dist-info/top_level.txt
salang-0.0.2.dist-info/RECORD
