Metadata-Version: 2.1
Name: salang
Version: 0.0.2
Summary: A langpack package
Home-page: https://github.com/samlet/salang
Author: Samlet Wu
Author-email: xiaofei.wu@gmail.com
License: UNKNOWN
Platform: UNKNOWN
Classifier: Programming Language :: Python :: 3
Classifier: License :: OSI Approved :: MIT License
Classifier: Operating System :: OS Independent
Requires-Python: >=3.6
Requires-Dist: py4j
Requires-Dist: simplejson
